{
  "memorias": [
    {
      "id": "1",
      "conteudo": "Usuário Principal",
      "tipo": "usuario",
      "timestamp": "2026-06-21T01:50:10.484Z",
      "visualWeight": 10,
      "lastAccessed": "2026-06-21T01:50:10.485Z",
      "accessCount": 15
    },
    {
      "id": "2",
      "conteudo": "GitHub",
      "tipo": "entidade",
      "timestamp": "2026-06-21T01:50:10.485Z",
      "visualWeight": 8,
      "lastAccessed": "2026-06-21T01:50:10.485Z",
      "accessCount": 12
    },
    {
      "id": "3",
      "conteudo": "Layon-System",
      "tipo": "fato",
      "timestamp": "2026-06-21T01:50:10.485Z",
      "visualWeight": 9,
      "lastAccessed": "2026-06-21T01:50:10.485Z",
      "accessCount": 14
    },
    {
      "id": "4",
      "conteudo": "Cérebro Digital",
      "tipo": "fato",
      "timestamp": "2026-06-21T01:50:10.485Z",
      "visualWeight": 9,
      "lastAccessed": "2026-06-21T01:50:10.485Z",
      "accessCount": 10
    },
    {
      "id": "5",
      "conteudo": "Inteligência Artificial",
      "tipo": "fato",
      "timestamp": "2026-06-21T01:50:10.485Z",
      "visualWeight": 8,
      "lastAccessed": "2026-06-21T01:50:10.485Z",
      "accessCount": 8
    },
    {
      "id": "6",
      "conteudo": "Aprendizado por Reforço",
      "tipo": "evento",
      "timestamp": "2026-06-21T01:50:10.485Z",
      "visualWeight": 7,
      "lastAccessed": "2026-06-21T01:50:10.485Z",
      "accessCount": 5
    },
    {
      "id": "7",
      "conteudo": "Memória Persistente",
      "tipo": "fato",
      "timestamp": "2026-06-21T01:50:10.485Z",
      "visualWeight": 8,
      "lastAccessed": "2026-06-21T01:50:10.485Z",
      "accessCount": 6
    },
    {
      "id": "8",
      "conteudo": "Grafo de Conhecimento",
      "tipo": "entidade",
      "timestamp": "2026-06-21T01:50:10.485Z",
      "visualWeight": 7,
      "lastAccessed": "2026-06-21T01:50:10.485Z",
      "accessCount": 4
    },
    {
      "id": "9",
      "conteudo": "Retorno de Feedback",
      "tipo": "sentimento",
      "timestamp": "2026-06-21T01:50:10.485Z",
      "visualWeight": 6,
      "lastAccessed": "2026-06-21T01:50:10.485Z",
      "accessCount": 3
    },
    {
      "id": "skill_mem_skill_1",
      "conteudo": "Skill: 3D Orbit Motion Landing Page 🧬",
      "tipo": "entidade",
      "timestamp": "2026-06-21T01:50:10.487Z",
      "visualWeight": 6,
      "lastAccessed": "2026-06-21T01:50:10.487Z",
      "accessCount": 1
    },
    {
      "id": "skill_mem_skill_2",
      "conteudo": "Skill: Stretching Elastic Dashboard ⚡",
      "tipo": "entidade",
      "timestamp": "2026-06-21T01:50:10.489Z",
      "visualWeight": 6,
      "lastAccessed": "2026-06-21T01:50:10.489Z",
      "accessCount": 1
    },
    {
      "id": "skill_mem_skill_3",
      "conteudo": "Skill: 21st.dev Prompt & Code Adaptor 🌟",
      "tipo": "entidade",
      "timestamp": "2026-06-21T01:50:10.491Z",
      "visualWeight": 6,
      "lastAccessed": "2026-06-21T01:50:10.491Z",
      "accessCount": 1
    },
    {
      "id": "design_mem_design_1",
      "conteudo": "Design: CyberHelix: BioTech 3D Core",
      "tipo": "entidade",
      "timestamp": "2026-06-21T01:50:10.493Z",
      "visualWeight": 6,
      "lastAccessed": "2026-06-21T01:50:10.493Z",
      "accessCount": 1
    },
    {
      "id": "design_mem_design_2",
      "conteudo": "Design: Minimalist Elastic Clock Dashboard ⏰",
      "tipo": "entidade",
      "timestamp": "2026-06-21T01:50:10.494Z",
      "visualWeight": 6,
      "lastAccessed": "2026-06-21T01:50:10.495Z",
      "accessCount": 1
    }
  ],
  "relacoes": [
    {
      "id": "r1",
      "origem_id": "1",
      "destino_id": "2",
      "peso": 10,
      "tipo_relacao": "Instagram"
    },
    {
      "id": "r2",
      "origem_id": "1",
      "destino_id": "3",
      "peso": 9,
      "tipo_relacao": "Desenvolveu"
    },
    {
      "id": "r3",
      "origem_id": "1",
      "destino_id": "4",
      "peso": 8,
      "tipo_relacao": "Criador"
    },
    {
      "id": "r4",
      "origem_id": "4",
      "destino_id": "5",
      "peso": 9,
      "tipo_relacao": "Estuda"
    },
    {
      "id": "r5",
      "origem_id": "4",
      "destino_id": "7",
      "peso": 8,
      "tipo_relacao": "Operação"
    },
    {
      "id": "r6",
      "origem_id": "4",
      "destino_id": "8",
      "peso": 8,
      "tipo_relacao": "Visualiza"
    },
    {
      "id": "r7",
      "origem_id": "5",
      "destino_id": "6",
      "peso": 7,
      "tipo_relacao": "Usa"
    },
    {
      "id": "r8",
      "origem_id": "6",
      "destino_id": "9",
      "peso": 8,
      "tipo_relacao": "Processa"
    },
    {
      "id": "r9",
      "origem_id": "7",
      "destino_id": "8",
      "peso": 7,
      "tipo_relacao": "Mapeia"
    },
    {
      "id": "rel_skill_skill_1",
      "origem_id": "4",
      "destino_id": "skill_mem_skill_1",
      "peso": 7,
      "tipo_relacao": "Habilidade"
    },
    {
      "id": "rel_skill_skill_2",
      "origem_id": "4",
      "destino_id": "skill_mem_skill_2",
      "peso": 7,
      "tipo_relacao": "Habilidade"
    },
    {
      "id": "rel_skill_skill_3",
      "origem_id": "4",
      "destino_id": "skill_mem_skill_3",
      "peso": 7,
      "tipo_relacao": "Habilidade"
    },
    {
      "id": "rel_design_design_1",
      "origem_id": "4",
      "destino_id": "design_mem_design_1",
      "peso": 7,
      "tipo_relacao": "Design"
    },
    {
      "id": "rel_design_design_2",
      "origem_id": "4",
      "destino_id": "design_mem_design_2",
      "peso": 7,
      "tipo_relacao": "Design"
    }
  ],
  "feedbacks": [],
  "votos": {},
  "logs": [
    {
      "id": "log_1782006610495_mw8j",
      "timestamp": "2026-06-21T01:50:10.495Z",
      "acao": "MEMORIZAÇÃO",
      "detalhe": "Nova memória gravada: \"Design: Minimalist Elastic Clock Dashboard ⏰\" [Tipo: entidade]"
    },
    {
      "id": "log_1782006610493_hy5d",
      "timestamp": "2026-06-21T01:50:10.493Z",
      "acao": "MEMORIZAÇÃO",
      "detalhe": "Nova memória gravada: \"Design: CyberHelix: BioTech 3D Core\" [Tipo: entidade]"
    },
    {
      "id": "log_1782006610491_9vnu",
      "timestamp": "2026-06-21T01:50:10.491Z",
      "acao": "MEMORIZAÇÃO",
      "detalhe": "Nova memória gravada: \"Skill: 21st.dev Prompt & Code Adaptor 🌟\" [Tipo: entidade]"
    },
    {
      "id": "log_1782006610489_5ivh",
      "timestamp": "2026-06-21T01:50:10.489Z",
      "acao": "MEMORIZAÇÃO",
      "detalhe": "Nova memória gravada: \"Skill: Stretching Elastic Dashboard ⚡\" [Tipo: entidade]"
    },
    {
      "id": "log_1782006610487_mt5r",
      "timestamp": "2026-06-21T01:50:10.487Z",
      "acao": "MEMORIZAÇÃO",
      "detalhe": "Nova memória gravada: \"Skill: 3D Orbit Motion Landing Page 🧬\" [Tipo: entidade]"
    },
    {
      "id": "l1",
      "timestamp": "2026-06-21T01:50:10.485Z",
      "acao": "COGNICÃO",
      "detalhe": "Sistema Cognitivo Layon-System inicializado."
    },
    {
      "id": "l2",
      "timestamp": "2026-06-21T01:50:10.485Z",
      "acao": "MEMORIZAÇÃO",
      "detalhe": "Base inicial de conhecimento carregada na memória persistente."
    }
  ],
  "skills": [
    {
      "id": "skill_1",
      "name": "3D Orbit Motion Landing Page 🧬",
      "description": "Landing pages de alta fidelidade com efeitos de órbita 3D, menus expansivos inteligentes e tema Neon Cyberpunk.",
      "systemPrompt": "Você é um Lead Frontend Designer especializado em interfaces de alto nível visual e efeitos de Motion 3D estruturados em Tailwind CSS com SVGs interativos de órbita molecular.",
      "promptTemplate": "Crie uma Landing Page 3D para o setor de [Setor] com um painel de dados com efeitos de órbita molecular que se abre ao arrastar/clicar e blocos expansivos interativos.",
      "tags": [
        "Landing Page",
        "3D Motion",
        "Glow",
        "Bento Grid"
      ],
      "author": "João Layon",
      "timestamp": "2026-06-21T01:50:10.485Z"
    },
    {
      "id": "skill_2",
      "name": "Stretching Elastic Dashboard ⚡",
      "description": "Painéis flexíveis elásticos cujo layout se divide ou estica ao expandir métricas, revelando sub-panels interativos no clique.",
      "systemPrompt": "Você é um arquiteto de Dashboard interativo. Escreva aplicativos em que os componentes esticam e revelam tabelas ricas, botões de ação e dados estatísticos de forma fluida.",
      "promptTemplate": "Crie um dashboard com 3 widgets principais que se esticam horizontalmente de forma elástica quando ativados.",
      "tags": [
        "Dashboard",
        "Stretching UI",
        "Flex-Bento",
        "Logs"
      ],
      "author": "Layon-System",
      "timestamp": "2026-06-21T01:50:10.485Z"
    },
    {
      "id": "skill_3",
      "name": "21st.dev Prompt & Code Adaptor 🌟",
      "description": "Conversor de componentes do repositório de designs 21st.dev e layouts Tailwind para componentes funcionais purificados com Lucide-React.",
      "systemPrompt": "Você é um conversor especialista de componentes 21st.dev. Remova importações redundantes, garanta compatibilidade da biblioteca Lucide-React e implemente estados reativos completos.",
      "promptTemplate": "Refatore e incorpore o seguinte componente da 21st.dev para torná-lo espetacular: \n\n[CÓDIGO/PROMPT_COPIADO]",
      "tags": [
        "21st.dev",
        "Clean Code",
        "Refactoring",
        "Compatibilidade"
      ],
      "author": "João Layon",
      "timestamp": "2026-06-21T01:50:10.485Z"
    }
  ],
  "designs": [
    {
      "id": "design_1",
      "title": "CyberHelix: BioTech 3D Core",
      "description": "Uma landing page de bioinformática futurista com uma hélice de DNA 3D em SVG rotativo ativo, bento-grid de biossensores e dashboard molecular inteligente que estica ao toque.",
      "code": "App.tsx de Bioinformática com hélice rotativa 3D e expansão inteligente de seções",
      "files": [
        {
          "fileName": "App.tsx",
          "fileLanguage": "tsx",
          "fileContent": "import React, { useState } from 'react';\nimport { Brain, Heart, Activity, Shield, Cpu, RefreshCw, Zap, Plus, Layers, Sparkles } from 'lucide-react';\n\nexport default function App() {\n  const [selectedSensor, setSelectedSensor] = useState<string>('cortex');\n  const [pulseSpeed, setPulseSpeed] = useState<number>(3);\n  \n  const sensors = [\n    { id: 'cortex', name: 'Sincronizador Córtex', value: '98.4%', status: 'Nominal', desc: 'Conexão sináptica principal transmitindo telemetria neural.' },\n    { id: 'heart', name: 'Cardiorreceptor 3D', value: '72 bpm', status: 'Estável', desc: 'Monitoramento do fluxo cardíaco bioelétrico em tempo real.' },\n    { id: 'immune', name: 'Escudo Imunológico', value: '100%', status: 'Protegido', desc: 'Barreira nanotecnológica ativa protegendo sistemas vitais.' }\n  ];\n\n  return (\n    <div className=\"min-h-screen bg-[#05070a] text-[#e6edf3] p-4 font-sans select-none overflow-x-hidden flex flex-col justify-between\">\n      <header className=\"flex items-center justify-between p-4 bg-slate-950/80 rounded-xl border border-indigo-500/10 mb-6\">\n        <div className=\"flex items-center gap-2\">\n          <Activity className=\"w-5 h-5 text-purple-400 animate-pulse\" />\n          <span className=\"font-mono text-xs font-black tracking-widest text-[#00f2ff]\">CYBERHELIX PLATFORM</span>\n        </div>\n        <div className=\"flex items-center gap-2\">\n          <span className=\"bg-purple-950/50 text-purple-400 border border-purple-500/20 text-[9px] px-2.5 py-0.5 rounded-full font-bold\">BIOTECH IA v12.4</span>\n        </div>\n      </header>\n\n      <div className=\"grid grid-cols-1 lg:grid-cols-12 gap-6 flex-1\">\n        <div className=\"lg:col-span-5 bg-gradient-to-b from-[#0a0f1d] to-[#04060b] border border-cyan-500/10 rounded-2xl p-6 flex flex-col justify-between relative overflow-hidden min-h-[350px]\">\n          <div className=\"z-10\">\n            <span className=\"text-[9px] font-mono text-cyan-400 tracking-wider uppercase\">SIMULADOR MOLECULAR 3D</span>\n            <h3 className=\"text-lg font-bold font-display text-white mt-1\">Interação Tridimensional</h3>\n          </div>\n\n          <div className=\"flex-1 flex items-center justify-center relative my-4\">\n            <div className=\"absolute inset-0 bg-[radial-gradient(circle_at_center,rgba(139,92,246,0.1)_0%,transparent_60%)] pointer-events-none\" />\n            \n            <svg viewBox=\"0 0 300 160\" className=\"w-full max-w-[280px] drop-shadow-[0_0_15px_rgba(0,242,255,0.25)]\">\n              <g>\n                <circle cx=\"150\" cy=\"80\" r=\"65\" stroke=\"rgba(0,242,255,0.15)\" strokeWidth=\"1\" fill=\"none\" strokeDasharray=\"3,3\" />\n                <circle cx=\"150\" cy=\"80\" r=\"35\" stroke=\"rgba(189,0,255,0.1)\" strokeWidth=\"1\" fill=\"none\" />\n              </g>\n\n              {[...Array(9)].map((_, i) => {\n                const x = 50 + i * 25;\n                const phase = i * 0.7;\n                return (\n                  <g key={i}>\n                    <line x1={x} y1=\"30\" x2={x} y2=\"130\" stroke=\"rgba(30,41,59,0.5)\" strokeWidth=\"1.5\" />\n                    <line \n                      x1={x} \n                      y1={80 + Math.sin(phase) * 35} \n                      x2={x} \n                      y2={80 - Math.sin(phase) * 35} \n                      stroke=\"rgba(0,242,255,0.3)\" \n                      strokeWidth=\"2\"\n                    />\n                    \n                    <circle cx={x} cy={80 + Math.sin(phase) * 35} r=\"5.5\" fill=\"#00f2ff\" />\n                    <circle cx={x} cy={80 - Math.sin(phase) * 35} r=\"4.5\" fill=\"#bd00ff\" />\n                  </g>\n                );\n              })}\n            </svg>\n          </div>\n\n          <div className=\"z-10 bg-black/40 p-3 rounded-lg border border-slate-900 flex justify-between items-center mt-2\">\n            <span className=\"text-[10px] font-mono text-gray-400\">Velocidade da Órbita:</span>\n            <div className=\"flex gap-1.5\">\n              {[5, 3, 1].map((speed, idx) => (\n                <button\n                  key={speed}\n                  onClick={() => setPulseSpeed(speed)}\n                  className={`text-[9px] font-mono py-1 px-2.5 bg-black border ${\n                    pulseSpeed === speed ? \"text-cyan-400 border-cyan-500/40\" : \"text-gray-500 border-gray-900\"\n                  }`}\n                >\n                  {[\"Lento\", \"Médio\", \"Rápido\"][idx]}\n                </button>\n              ))}\n            </div>\n          </div>\n        </div>\n\n        <div className=\"lg:col-span-7 flex flex-col gap-4 font-sans\">\n          <span className=\"text-[9px] font-mono text-purple-400 uppercase tracking-widest font-black block\">SENSORES COGNITIVOS BIO-INTEGRADOS</span>\n          \n          <div className=\"grid grid-cols-1 md:grid-cols-3 gap-4\">\n            {sensors.map(s => {\n              const isSelected = selectedSensor === s.id;\n              return (\n                <div\n                  key={s.id}\n                  onClick={() => setSelectedSensor(s.id)}\n                  className={`p-4 rounded-xl border transition cursor-pointer flex flex-col gap-2 bg-[#090b11] ${\n                    isSelected ? \"border-cyan-500/40 shadow-lg shadow-cyan-950/20\" : \"border-slate-900 hover:border-slate-800\"\n                  }`}\n                >\n                  <div className=\"flex justify-between items-center\">\n                    <span className=\"text-[10px] font-mono font-bold text-gray-500\">{s.status}</span>\n                    <Sparkles className={`w-3 h-3 ${isSelected ? \"text-cyan-400\" : \"text-gray-600\"}`} />\n                  </div>\n                  <h4 className=\"text-xs font-bold text-slate-100\">{s.name}</h4>\n                  <span className=\"text-lg font-mono font-black text-white\">{s.value}</span>\n                </div>\n              );\n            })}\n          </div>\n\n          <div className=\"bg-[#090b11] border border-violet-950/40 rounded-xl p-5 flex flex-col gap-3 flex-1 select-text\">\n            <div className=\"flex items-center gap-2 select-none\">\n              <Layers className=\"w-4 h-4 text-purple-400\" />\n              <span className=\"text-xs font-mono font-black uppercase text-purple-300\">Análise Molecular Expandida</span>\n            </div>\n            \n            <p className=\"text-xs text-gray-300 leading-relaxed\">\n              {sensors.find(s => s.id === selectedSensor)?.desc} O ambiente cognitivo de João Layon de forma autoral estica essa telemetria.\n            </p>\n\n            <div className=\"mt-2 bg-black/60 p-4 rounded-lg border border-gray-900 font-mono text-[10px] text-[#00ff9d] flex flex-col gap-1\">\n              <div className=\"flex justify-between text-[8.5px] text-gray-500\">\n                <span>PARÂMETRO SENSOR</span>\n                <span>RETORNO HEX</span>\n              </div>\n              <div className=\"flex justify-between\">\n                <span>HEURISTIC_DNA_PAIR</span>\n                <span>0xFE241031B50D</span>\n              </div>\n            </div>\n          </div>\n        </div>\n      </div>\n    </div>\n  );\n}"
        },
        {
          "fileName": "database.ts",
          "fileLanguage": "typescript",
          "fileContent": "export const db = { sensors: [] };"
        }
      ],
      "compilationLogs": [
        "[simulation] CyberHelix compilado com sucesso.",
        "[simulation] renderizando elemento 3D rotativo."
      ],
      "interactiveVariables": {
        "speed": 3
      },
      "promptUsed": "Crie uma landing page com hélice rotativa",
      "skillIdUsed": "skill_1",
      "timestamp": "2026-06-21T01:50:10.485Z"
    },
    {
      "id": "design_2",
      "title": "Minimalist Elastic Clock Dashboard ⏰",
      "description": "Interface de relógio e produtividade em que as seções se esticam e encolhem elástica e dinamicamente de acordo com fuso-horários selecionados, com contador de pomodoro integrado!",
      "code": "Painel com fuso-horário e pomodoro",
      "files": [
        {
          "fileName": "App.tsx",
          "fileLanguage": "tsx",
          "fileContent": "import React, { useState, useEffect } from 'react';\nimport { Watch, Play, Pause, RefreshCw } from 'lucide-react';\n\nexport default function App() {\n  const [time, setTime] = useState(new Date().toLocaleTimeString());\n  const [activeZone, setActiveZone] = useState('BR');\n  const [seconds, setSeconds] = useState(1500);\n  const [timerActive, setTimerActive] = useState(false);\n\n  useEffect(() => {\n    const t = setInterval(() => {\n      const now = new Date();\n      if (activeZone === 'BR') {\n        setTime(now.toLocaleTimeString(\"pt-BR\"));\n      } else if (activeZone === 'NY') {\n        setTime(now.toLocaleTimeString(\"en-US\", { timeZone: \"America/New_York\" }));\n      } else {\n        setTime(now.toLocaleTimeString(\"en-US\", { timeZone: \"Europe/London\" }));\n      }\n    }, 1000);\n    return () => clearInterval(t);\n  }, [activeZone]);\n\n  useEffect(() => {\n    let t: any;\n    if (timerActive && seconds > 0) {\n      t = setInterval(() => setSeconds(s => s - 1), 1000);\n    }\n    return () => clearInterval(t);\n  }, [timerActive, seconds]);\n\n  const formatSeconds = (sec: number) => {\n    const m = Math.floor(sec / 60).toString().padStart(2, '0');\n    const s = (sec % 60).toString().padStart(2, '0');\n    return `${m}:${s}`;\n  };\n\n  return (\n    <div className=\"min-h-screen bg-[#03060c] text-slate-100 p-6 font-mono flex flex-col justify-between\">\n      <div className=\"flex items-center justify-between border-b border-gray-900 pb-3 mb-6\">\n        <span className=\"text-[10px] tracking-widest font-bold uppercase text-emerald-300\">ESTAÇÃO CHRONOS</span>\n        <span className=\"text-[9px] text-gray-500\">ZONAS DINÂMICAS</span>\n      </div>\n\n      <div className=\"grid grid-cols-1 lg:grid-cols-2 gap-6 flex-1\">\n        <div className=\"bg-black/60 border border-gray-900 rounded-2xl p-6 flex flex-col justify-between\">\n          <div>\n            <span className=\"text-[8px] uppercase text-gray-500\">Horizonte de Fuso</span>\n            <h3 className=\"text-base font-bold text-white mt-1\">Multi-Fuso Elástico</h3>\n          </div>\n\n          <div className=\"my-6 text-center\">\n            <span className=\"text-3xl font-black text-white hover:text-cyan-400 transition tracking-wider block\">{time}</span>\n          </div>\n\n          <div className=\"flex justify-center gap-2\">\n            {['BR', 'NY', 'LDN'].map(zone => (\n              <button\n                key={zone}\n                onClick={() => { setActiveZone(zone); }}\n                className={`px-4 py-2 rounded-lg border text-xs cursor-pointer transition-all ${\n                  activeZone === zone ? 'bg-[#00ff9d]/20 text-[#00ff9d] border-[#00ff9d]/40' : 'bg-transparent border-gray-800 text-gray-400'\n                }`}\n              >\n                {zone}\n              </button>\n            ))}\n          </div>\n        </div>\n\n        <div className=\"bg-black/60 border border-gray-900 rounded-2xl p-6 flex flex-col justify-between\">\n          <div>\n            <span className=\"text-[8px] uppercase text-gray-400\">Concentração</span>\n            <h3 className=\"text-base font-bold text-white mt-1\">Pomodoro</h3>\n          </div>\n\n          <div className=\"my-6 text-center\">\n            <span className=\"text-4xl font-black text-purple-400 block tracking-widest\">{formatSeconds(seconds)}</span>\n          </div>\n\n          <div className=\"flex justify-center gap-2\">\n            <button\n              onClick={() => setTimerActive(!timerActive)}\n              className=\"bg-purple-600 hover:bg-purple-500 text-white text-xs px-4 py-2 rounded flex items-center gap-1 cursor-pointer animate-pulse\"\n            >\n              TIMER\n            </button>\n          </div>\n        </div>\n      </div>\n    </div>\n  );\n}"
        }
      ],
      "compilationLogs": [
        "[simulation] Chronos Clock compiled successfully."
      ],
      "interactiveVariables": {
        "activeZone": "BR"
      },
      "promptUsed": "Crie um dashboard com relógio fuso e pomodoro",
      "skillIdUsed": "skill_2",
      "timestamp": "2026-06-21T01:50:10.485Z"
    }
  ],
  "configuracoes": {
    "GEMINI_API_KEY": "AIzaTestKey1234"
  }
}